shexer/__init__.py
shexer/__main__.py
shexer/cli.py
shexer/consts.py
shexer/shaper.py
shexer/core/__init__.py
shexer/core/instances/__init__.py
shexer/core/instances/abstract_instance_tracker.py
shexer/core/instances/endpoint_instance_tracker.py
shexer/core/instances/federated_source_instance_tracker.py
shexer/core/instances/instance_tracker.py
shexer/core/instances/pconsts.py
shexer/core/instances/annotators/__init__.py
shexer/core/instances/annotators/annotator_func.py
shexer/core/instances/annotators/annotator_tracking_instances.py
shexer/core/instances/annotators/base_annotator.py
shexer/core/instances/annotators/strategy_mode/__init__.py
shexer/core/instances/annotators/strategy_mode/all_classes_mode.py
shexer/core/instances/annotators/strategy_mode/base_strategy_mode.py
shexer/core/instances/annotators/strategy_mode/compound_strategy_mode.py
shexer/core/instances/annotators/strategy_mode/instance_cap_mode.py
shexer/core/instances/annotators/strategy_mode/instances_cap_exception.py
shexer/core/instances/annotators/strategy_mode/shape_qualifiers_mode.py
shexer/core/instances/annotators/strategy_mode/target_classes_mode.py
shexer/core/instances/mappings/__init__.py
shexer/core/instances/mappings/shape_map_instance_tracker.py
shexer/core/instances/mix/__init__.py
shexer/core/instances/mix/mixed_instance_tracker.py
shexer/core/profiling/__init__.py
shexer/core/profiling/class_profiler.py
shexer/core/profiling/consts.py
shexer/core/profiling/federated_source_class_profiler.py
shexer/core/profiling/strategy/__init__.py
shexer/core/profiling/strategy/abstract_feature_direction_strategy.py
shexer/core/profiling/strategy/direct_features_strategy.py
shexer/core/profiling/strategy/include_reverse_features_strategy.py
shexer/core/shexing/__init__.py
shexer/core/shexing/class_shexer.py
shexer/core/shexing/class_shexer_fed_sources.py
shexer/core/shexing/strategy/__init__.py
shexer/core/shexing/strategy/abstract_shexing_strategy.py
shexer-2.7.2.dist-info/licenses/LICENSE
shexer-2.7.2.dist-info/METADATA
shexer-2.7.2.dist-info/WHEEL
shexer-2.7.2.dist-info/top_level.txt
shexer-2.7.2.dist-info/RECORD
