Metadata-Version: 2.4
Name: shexer
Version: 2.7.2
Summary: Automatic schema extraction for RDF graphs
Home-page: https://github.com/DaniFdezAlvarez/shexer
Download-URL: https://github.com/DaniFdezAlvarez/shexer/archive/2.7.2.tar.gz
Author: Daniel Fernandez-Alvarez
Author-email: danifdezalvarez@gmail.com
Keywords: testing,shexer,shexerp3,rdf,shex,shacl,schema
Classifier: Programming Language :: Python :: 3.7
Classifier: Programming Language :: Python :: 3.8
Classifier: Programming Language :: Python :: 3.9
Classifier: Programming Language :: Python :: 3.10
Classifier: Programming Language :: Python :: 3.11
Classifier: Intended Audience :: Science/Research
Classifier: Intended Audience :: Information Technology
Classifier: Topic :: Software Development :: Libraries :: Python Modules
License-File: LICENSE
Requires-Dist: Flask
Requires-Dist: Flask-Cors
Requires-Dist: rdflib
Requires-Dist: SPARQLWrapper
Requires-Dist: wlighter
Requires-Dist: plantuml
Requires-Dist: python-xz
Dynamic: author
Dynamic: author-email
Dynamic: classifier
Dynamic: description
Dynamic: description-content-type
Dynamic: download-url
Dynamic: home-page
Dynamic: keywords
Dynamic: license-file
Dynamic: requires-dist
Dynamic: summary
